{"input": "Extraia as informações relevantes desta Ata de Registro de Preços (ARP) e os estruture estritamente no formato JSON. \nAs informações relevantes podem ser o número da ata, número do processo, data de emissão, identificação do fornecedor ou uma lista de múltiplos\nprodutos com seus preços, descrições e quantias e valor total.\nGaranta que todos os campos vazios sejam preenchidos com os dados correspondentes encontrados no texto de entrada. \nO campo \"Itens_Registrados\" é uma lista JSON e pode conter um ou mais itens.\nPara campos que se referem a quantidades, valores e percentuais, utilize o formato exato encontrado no documento.\nRetorne somente o esquema JSON.\n\n\nDocumento:\nAvenida da Paz, n 900 Jaraguá - MaceióAL - CEP 57022-050 CNPJ n 26.981.4550001-29 - Telefone: (82) 3312-5100 ATA DE REGISTRO DE PREÇO N 4822025- CPLALICC PREGÃO ELETRÔNICO (ARP) N 1342025-CPLALICC PROCESSO ADMINISTRATIVO N 12500.1296882024 O MUNICIPIO DE MACEIÓ por intermédio da AGÊNCIA DE LICITAÇÕES, CONTRATOS E CONVÊNIOS DE MACEIÓ ALICC, CNPJ n. 26.981.4550001-29, situada na Avenida da Paz, n. 900, Jaraguá, MaceióAL 57.022-050 neste ato representada pela Diretora Presidente, MEIRY SOARES PORCIÚNCULA, doravante denominada ÓRGÃO GERENCIADOR, institui a presente ARP - Ata de Registro de Preços, decorrente da licitação na modalidade de Pregão Eletrônico, sob o n n 1342025 CPLALICC, do tipo MENOR PREÇO, processada nos termos do Processo Administrativo n. 12500.1296882024, a qual se constitui em documento vinculativo e obrigacional às partes, à luz da permissão inserta no art. 14, inc. II da Lei Federal n. 141332021 regulamentados pelos Decretos Municipais ns. 9.5142023 e 8.4152017, segundo as cláusulas e condições seguintes: 1. DO OBJETO 1.1 A presente ARP tem por objeto o Registro de preços para futura e eventual contratação de empresa especializada no Fornecimento de Gêneros Alimentícios (2), para atender a demanda dos órgãos da Administração Pública do Município de Maceió, especificado no Termo de Referência, Anexo I do Edital de Pregão n 1342025 que é parte integrante desta Ata, assim como a proposta vencedora, independentemente de transcrição. 2. DOS PREÇOS, ESPECIFICAÇÕES E QUANTITATIVOS 2.1 Esta ARP estabelece as cláusulas e condições gerais para o registro de preços cuja(s) especificações técnicas, marca(s)modelo(s), preço(s), quantitativo(s) e fornecedor(es) foram previamente definidos por meio do procedimento licitatório supracitado, conforme abaixo descrito resumidamente: Fornecedor Beneficiário: J O DE A L C LTDA CNPJ: 44.346.5370001-83 Endereço: Av. Siqueira Campos N1747 A, Bairro: Trapiche Da Barra, MaceióAL - CEP: 57010-395 Telefones: (82)-988743536 Representante Legal: Juliana Olivia de Azevedo Lima Câmara Identidade e CPF: RG: 4284497-5 SSPAL CPF 058.119.514-00 E-mail: edvaldocamaragmail.com\nAvenida da Paz, n 900 Jaraguá - MaceióAL - CEP 57022-050 CNPJ n 26.981.4550001-29 - Telefone: (82) 3312-5100 COTA PRINCIPAL (AMPLA PARTICIPAÇÃO) 89 Item Descrição do Produto Unid. Quant. Marca Fabricante Valor Unitário R Valor Total R 19 Extrato de tomate - a base de: tomate, açúcar (máximo de 1), sal (máximo de 5 de cloreto de sódio); isento de fermentações. O produto deverá apresentar validade mínima de 12 meses da entrega. Embalagem de 1080g Und 8722 Quero 12,99 113.298,7 8 20 Sardinha comestível em lata - em conserva, tipo pescada em conserva, apresentação inteira, com espinha e óleo comestível, contendo ômega 3. Embalagem contendo o registro e informações nutricionais do Ministério da Agricultura, data de validade e o SIFDIPOA. O produto deverá apresentar validade mínima de 12 meses da entrega. Embalagem de 200g. Und 22606 GDC Alimentos 4,95 111.899,7 0 COTA RESERVADA (PARTICIPAÇÃO ME E EPP) 11 Item Descrição do Produto Unid. Quant. Marca Fabricante Valor Unitário R Valor Total R 27 Manteiga com sal, contendo dados de identificação do produto, marca do fabricante, prazo de validade e peso líquido. O produto deverá ter registro no Ministério da Saúde eou Agricultura, em embalagens e temperaturas corretas (10c ou de acordo com o fabricante) e adequadas, respeitando a características do produto. De modo que a embalagem não se apresente estufadas ou alteradas. Embalagem com 200g, Und 4488 Betânia 11,99 53.811,12 28 Biscoito tipo cream cracker 400g - biscoito com sal, elaborado com composição básica de farinha de trigo, sal, enriquecida com ferro e ácido fólico, outras substâncias permitidas, acondicionado em embalagem primária plástica atóxica, íntegra, transparente; rótulo contendo: identificação do produto, ingredientes, valor Pct 1840 3 de Maio 4,44 8.169,60\nAvenida da Paz, n 900 Jaraguá - MaceióAL - CEP 57022-050 CNPJ n 26.981.4550001-29 - Telefone: (82) 3312-5100 nutricional, peso, fabricante, data de fabricação. O produto deverá apresentar validade mínima de 6 meses da entrega. Pacote de 400g. 31 Sardinha comestível em lata - em conserva, tipo pescada em conserva, apresentação inteira, com espinha e óleo comestível, contendo ômega 3. Embalagem contendo o registro e informações nutricionais do Ministério da Agricultura, data de validade e o SIFDIPOA. O produto deverá apresentar validade mínima de 12 meses da entrega. Embalagem de 200g. Und 2794 GDC Alimentos 4,95 13.830,30 2.2 O valor total desta Ata é de R 301.009,50 (trezentos e um mil e nove reais e cinquenta centavos). 2.3 Ao participar do procedimento licitatório, o fornecedor obriga-se ao cumprimento de todos os encargos estabelecidos na presente ARP, nos exatos termos do resultado final obtido no procedimento licitatório, quanto ao preço, a quantidade e as especificações do objeto registrado, integrando e complementado a presente ARP. 2.4 Também fica formalizado, conjuntamente com a presente ARP, o CADASTRO DE RESERVA de (ATÉ DOIS) fornecedor(es) interessado(s) em eventualmente assumir a titularidade do registro de preços, havendo CANCELAMENTO de registro e segundo a ordem de classificação final no certame. 2.4.1 A formação de CADASTRO DE RESERVA vincula o(s) particular(es) aos termos da proposta do titular em relação ao preço, obrigando-se a assumir a titularidade do registro em caso de cancelamento do registro do titular, observada a ordem de classificação. Anexo B desta ARP. 2.5 Será realizada periódica pesquisa de mercado para a comprovação de vantajosidade desta Ata. 2.6 A alteração da titularidade do registro dependerá da comprovação das condições de participação do particular registrado no cadastro reserva, da qualidade do objeto indicado na sua proposta e do cumprimento das condições de habilitação, nos termos fixados no Edital PE n 1342025 CPLALICC. 2.7 Havendo alteração da titularidade do registro com base no CADASTRO DE RESERVA, deverá a ARP ser republicada para fins de eficácia 2.8 Os quantitativos registrados e endereços de entrega do órgão gerenciador e dos órgãos participantes estão dispostos em anexo a este documento.\nAvenida da Paz, n 900 Jaraguá - MaceióAL - CEP 57022-050 CNPJ n 26.981.4550001-29 - Telefone: (82) 3312-5100 3. DO ÓRGÃO GERENCIADOR E PARTICIPANTES 3.1 Os órgão(s) e entidade(s), abaixo relacionado(s), com seus respectivos endereços, integram a presente ARP como titulares, na condição de participantes: (Anexo desta ARP) 4. DA UTILIZAÇÃO DA ATA DE REGISTRO DE PREÇOS POR ÓRGÃO OU ENTIDADES NÃO PARTICIPANTES 4.1 A ata de registro de preços, durante sua vigência, poderá ser utilizada por qualquer órgão ou entidade do Município de Maceió, na condição de não participantes, desde que devidamente justificada a vantagem e espeitadas, no que couber, as condições e as regras estabelecidas no art. 22 do Decreto Municipal n 9.5142023. 4.2 É vedada aos órgãos e entidades da administração pública federal e estadual a adesão a ata de registro de preços gerenciada pela ALICC, salvo órgão ou entidade integrante do município de Maceió ou de outra esfera municipal. 4.3 Caberá ao fornecedor beneficiário da Ata de Registro de Preços, observadas as condições nela estabelecidas, optar pela aceitação ou não do fornecimento, desde que este fornecimento não prejudique as obrigações anteriormente assumidas com o órgão gerenciador e órgãos participantes. 4.4 As aquisições ou contratações adicionais a que se refere este item não poderão exceder, por órgão ou entidade, a 50 (cinquenta) por cento dos quantitativos dos itens do instrumento convocatório e registrados na ata de registro de preços para o órgão gerenciador e órgãos participantes. 4.5 As adesões à ata de registro de preços são limitadas, na totalidade, não pode exceder ao dobro do quantitativo de cada item registrado na ata de registro de preços para o órgão gerenciador e órgãos participantes, independentemente do número de órgãos não participantes que eventualmente aderirem. 4.6 Ao órgão não participante que aderir à ata competem os atos relativos à cobrança do cumprimento pelo fornecedor das obrigações contratualmente assumidas e a aplicação, observada a ampla defesa e o contraditório, de eventuais penalidades decorrentes do descumprimento de cláusulas contratuais, em relação as suas próprias contratações, informando as ocorrências ao órgão gerenciador. 4.7 Após a autorização do órgão gerenciador, o órgão não participante deverá efetivar a contratação solicitada em até noventa dias, observado o prazo de validade da Ata de Registro de Preços. 4.8 Caberá ao órgão gerenciador autorizar, excepcional e justificadamente, a prorrogação do prazo para efetivação da contratação, respeitado o prazo de vigência da ata, desde que solicitada pelo órgão não participante. 5 DO REMANEJAMENTO: 5.1 Nas Atas de Registro de Preço, as quantidades previstas para os itens com preços registrados poderão ser remanejadas pelo órgão gerenciador entre os órgãos participantes e não participantes do procedimento licitatório para registro de preços. 5.2 O remanejamento somente poderá ser feito de órgão participante para órgão participante e de órgão participante para órgão não participante. 5.3 No caso de remanejamento de órgão participante para órgão não participante, devem ser observados os limites previstos nos do Decreto Municipal n 9.5142023.\nAvenida da Paz, n 900 Jaraguá - MaceióAL - CEP 57022-050 CNPJ n 26.981.4550001-29 - Telefone: (82) 3312-5100 5.4 Caberá ao Órgão Gerenciador autorizar o remanejamento solicitado, com a redução do quantitativo inicialmente informado pelo órgão participante, desde que haja prévia anuência do órgão que vier a sofrer redução dos quantitativos informados. 5.5 Os remanejamentos somente ocorrerão entre órgãos e entidades da Administração Pública Municipal de Maceió. 6 DA VALIDADE DA ATA 6.1 O prazo de validade desta ata de registro de preços será de 1 (um) ano e poderá ser prorrogado, por igual período, desde que comprovado o preço vantajoso, contados a partir da data sua publicação no Diário Oficial Eletrônico do Município de Maceió - DOEM, salvo as hipóteses de cancelamento contidas nos arts. 20 e 21 do Decreto n 9.5142023. 5.1.1 É vedado efetuar acréscimos nos quantitativos fixados pela ata de registro de preços. 7 DA CONTRATAÇÃO COM FORNECEDORES REGISTRADOS 7.1 As contratações decorrentes da presente ARP poderão ser realizadas diretamente pelo órgão gerenciador eou por cada um dos participantes, observados os quantitativos respectivamente previstos para cada procedimento de licitação, e as demais exigências e formalidades previstas na legislação e na jurisprudência do TCU. 7.2 A contratação com os fornecedores registrados será formalizada pelo órgão interessado por intermédio de instrumento contratual, emissão de nota de empenho de despesa, autorização de compra ou outro instrumento hábil, conforme o art. 92 da Lei n 14.133, de 2021. 8 DAS OBRIGAÇÕES DAS PARTES 8.1 DO ÓRGÃO GERENCIADOR: I. O ÓRGÃO GERENCIADOR promoverá o gerenciamento permanente e formal da presente ARP, inclusive com registro, em processo administrativo de gestão específico, relativo a todas as contratações dela decorrentes, como também de todos os demais atos inerentes aos procedimentos de gestão. II. Cabe à Gerência de Contratos e Atas do ÓRGÃO GERENCIADOR, conforme regulamento operacional interno, as atribuições inerentes ao GERENCIAMENTO da presente ARP, particularmente quanto a (ao): a) Providenciar a elaboração e publicação da presente ARP; b) Encaminhar ao(s) órgão(s) eou entidade(s) participantes a presente ARP, devidamente assinada e publicada, como também suas eventuais e posteriores alterações, devidamente assinadas e publicadas; c) Controlar, de forma permanente, a utilização da ARP para fins de contratações, durante toda sua vigência; d) Receber, analisar e pronunciar-se quanto à solicitação de contratação interna do ÓRGÃO GERENCIADOR com base na presente ARP, inclusive indicando providências complementares necessárias ou até recomendando o indeferimento fundamentado da pretensão, observada a legislação vigente e a jurisprudência do TCU; e) Conduzir eventuais procedimentos de renegociação de preços registrados para fins de adequação às novas condições de mercado, observada a legislação vigente e jurisprudência do TCU;\nAvenida da Paz, n 900 Jaraguá - MaceióAL - CEP 57022-050 CNPJ n 26.981.4550001-29 - Telefone: (82) 3312-5100 f) Propor, conduzir e pronunciar-se nos procedimentos de eventuais alterações de preços, cancelamentos e revogações ocorridos na presente ARP, bem como realizar, nesses casos, a comunicação aos órgãos e às entidades participantes; g) Propor aplicação, garantida a ampla defesa e o contraditório, de penalidades decorrentes do descumprimento das obrigações assumidas na ARP, ou até em relação ao descumprimento das obrigações contratuais, unicamente referentes às contratações realizadas pelo ÓRGÃO GERENCIADOR; h) Instruir os autos de gestão da presente ARP. 8.2 DO ÓRGÃO PARTICIPANTE: I. Ao órgão ou entidade PARTICIPANTE cabe: a) Tomar conhecimento da ARP, incluindo as eventuais alterações, cancelamentos e revogações, a fim de utilizá-la de forma correta; b) Verificar a conformidade das condições registradas na ARP junto ao mercado local, informando ao ÓRGÃO GERENCIADOR eventuais desvantagens verificadas para fins de renegociações de preços; c) Observar e controlar a utilização do quantitativo máximo dos itensgrupos do objeto registrados em seu interesse, evitando contratações acima do limite permitido, bem como a utilização de itensgrupo diversos daqueles para os quais solicitou participação no certame; d) Acompanhar e fiscalizar o fiel cumprimento das obrigações contidas no edital da licitação e na ARP, informando ao ÓRGÃO GERENCIADOR qualquer irregularidade ou inadimplemento do particular; e) Aplicar, garantida a ampla defesa e o contraditório, as penalidades decorrentes do descumprimento das obrigações contratuais em relação às suas próprias contratações, informando as ocorrências ao ÓRGÃO GERENCIADOR. 8.3 DO BENEFICIÁRIO DA ATA: I. O FORNECEDOR cujo preço conste registrado na presente ARP obriga-se a: a) Retirar a respectiva nota de empenho ou ordem de serviço, bem como assinar o termo de contrato (se for caso), no prazo máximo de 05 dias corridos, contados da convocação; b) Caso seja consultado, informar a possibilidade de adesão de órgão ou entidade da Administração Pública não participante com finalidade de contratar por meio da presente ARP, tendo em vista a permissão expressa no Edital de PE n 1342025 CPLALICC; c) Observar rigorosamente todas as especificações técnicas, marcas, modelos, condições e prazos fixados no termo de referência integrante da presente ARP, como também na sua respectiva proposta de preços, ressalvado prova idônea da ocorrência superveniente de fato impeditivo ou dificultador do cumprimento da obrigação, devidamente aceito pelo ÓRGÃO GERENCIADOR, que justifique o fornecimento de bem de qualidade semelhante ou superior, ou a execução de forma diversa que resulte em igual ou superior resultado à contratante; d) Respeitar as demais condições e obrigações contidas nos documentos apresentados na licitação e em sua proposta, ressalvada a ocorrência de fato(s) superveniente(s), comprovados(s) e aceito(s) pelo ÓRGÃO GERENCIADOR;\nAvenida da Paz, n 900 Jaraguá - MaceióAL - CEP 57022-050 CNPJ n 26.981.4550001-29 - Telefone: (82) 3312-5100 e) Providenciar a imediata correção de deficiências, falhas ou irregularidades constatadas pelo ÓRGÃO GERENCIADOR eou pelo(s) PARTICIPANTE(S), referentes ao cumprimento das obrigações firmadas na presente ARP; f) Fornecer, sempre que solicitado, no prazo máximo de 05 dias corridos, documentação de habilitação e qualificação cujas validades encontrem-se vencidas para fins de viabilizar a(s) respectiva(s) contratações; g) Prover condições que possibilitem o atendimento das obrigações firmadas a partir da data de homologação do procedimento licitatório; h) Ressarcir os eventuais prejuízos causados aos órgãos e entidades contratantes eou a terceiros, provocados por ineficiência ou irregularidades cometidas na execução das obrigações assumidas na ARP; i) Responsabilizar-se pelos encargos trabalhistas, previdenciários, fiscais e comerciais resultantes da execução do contrato; j) Manter, durante a vigência da presente ata, em compatibilidade com as obrigações assumidas, todas as condições de habilitação e qualificação exigidas na licitação. 9 DA REVISÃO E DO CANCELAMENTO DA ATA 9.1 A qualquer tempo, o preço registrado poderá ser revisto em decorrência de eventual redução ocorrida no mercado, ou de fato que eleve o custo dos serviços ou bens registrados, em conformidade com o inciso IV, 5, do art. 82, da Lei N 14.133, de 202, cabendo ao ÓRGÃO GERENCIADOR providenciar a convocação do fornecedor registrado para negociar o novo valor compatível com o de mercado. 9.1.1 Não havendo acordo em relação a renegociação do(s) preço(s) registrado(s), será o respectivo registro cancelado, mantendo-se hígidas e vigentes as contratações já formalizadas e sem aplicação de penalidade. 9.1.2 Em caso do cancelamento para o respectivo itemGRUPO, deverão ser convocados os fornecedores registrados em cadastro reserva, a fim de que os mesmos manifestem interesse em assumir o compromisso de praticar o preço do fornecedor beneficiário da ata. 9.2 O registro será ser CANCELADO: I. Por iniciativa do ÓRGÃO GERENCIADOR, quando o fornecedor: a) Descumprir as condições da ata de registro de preços; b) Não retirar a nota de empenho ou instrumento equivalente no prazo estabelecido pela Administração, sem justificativa aceitável; c) Não aceitar reduzir o seu preço registrado, na hipótese deste se tornar superior àqueles praticados no mercado; ou; d) Sofrer sanção prevista nos incisos III ou IV do caput do art. 156 da Lei n 14.133, de 2021; II. Por iniciativa do próprio fornecedor, desde que apresente solicitação por escrito e anterior ao pedido de fornecimentocontratação, bem como comprove a impossibilidade de cumprimento das exigências insertas nesta ARP, tendo em vista fato superveniente, decorrente de caso fortuito ou força maior, aceito pelo ÓRGÃO GERENCIADOR, que comprovadamente venha a comprometer a perfeita execução contratual.\nAvenida da Paz, n 900 Jaraguá - MaceióAL - CEP 57022-050 CNPJ n 26.981.4550001-29 - Telefone: (82) 3312-5100 9.2.1 O cancelamento do registro, assegurados o contraditório e a ampla defesa, deverá ser formalizado nos autos do processo administrativo de gestão da presente ARP, por despacho fundamentado da autoridade competente no ÓRGÃO GERENCIADOR. 10 DAS PENALIDADES 10.1 Comete infração administrativa, nos termos da Lei n 14.133, de 2021, o contratado que: 10.1.1 Der causa à inexecução parcial do contrato; 10.1.2 Der causa à inexecução parcial do contrato que cause grave dano à Administração ou ao funcionamento dos serviços públicos ou ao interesse coletivo; 10.1.3 Der causa à inexecução total do contrato; 10.1.4 Ensejar o retardamento da execução ou da entrega do objeto da contratação sem motivo justificado; 10.1.5 Apresentar documentação falsa ou prestar declaração falsa durante a execução do contrato; 10.1.6 Praticar ato fraudulento na execução do contrato; 10.1.7 Comportar-se de modo inidôneo ou cometer fraude de qualquer natureza; 10.1.8 Praticar ato lesivo previsto no art. 5 da Lei n 12.846, de 1 de agosto de 2013. (Lei n 12.846 de 01 de Agosto de 2013 Dispõe sobre a responsabilização administrativa e civil de pessoas jurídicas pela prática de atos contra a administração pública, nacional ou estrangeira, e dá outras providências). 10.2 Comete infração administrativa, nos termos da Lei n 14.133, de 2021, o contratado que: 10.2.1 Advertência, quando o contratado der causa à inexecução parcial do contrato, sempre que não se justificar a imposição de penalidade mais grave (art. 156, 2, da Lei n 14.133, de 2021); 10.2.2 Impedimento de licitar e contratar, quando praticadas as condutas descritas nas alíneas b, c e d do subitem acima deste Contrato, sempre que não se justificar a imposição de penalidade mais grave (art. 156, 4, da Lei n 14.133, de 2021); 10.2.3 Declaração de inidoneidade para licitar e contratar, quando praticadas as condutas descritas nas alíneas e, f, g e h do subitem acima deste Termo de Referência, bem como nas alíneas b, c e d, que justifiquem a imposição de penalidade mais grave (art. 156, 5, da Lei n 14.133, de 2021). 10.2.4 Multa: 10.2.4.1 Moratória de 1 (um por cento) ao dia de atraso injustificado sobre o valor da parcela inadimplida, até o limite de dias; 10.2.4.2 Moratória de 1 (um por cento) por dia de atraso injustificado sobre o valor total do contrato, até o máximo de 20 (vinte por cento), pela inobservância do prazo fixado para apresentação, suplementação ou reposição da garantia. 10.2.4.3 O atraso superior a 10 (dez) dias autoriza a Administração a promover a extinção do contrato por descumprimento ou cumprimento irregular de suas cláusulas, conforme dispõe o inciso I do art. 137 da Lei n. 14.133, de 2021. 10.2.4.4 Compensatória de 20 (vinte por cento) sobre o valor total do contrato, no caso de inexecução total do objeto.\nAvenida da Paz, n 900 Jaraguá - MaceióAL - CEP 57022-050 CNPJ n 26.981.4550001-29 - Telefone: (82) 3312-5100 10.3 A aplicação das sanções previstas nesta Ata de Registro de Preços não exclui, em hipótese alguma, a obrigação de reparação integral do dano causado ao Contratante (art. 156, 9, da Lei n 14.133, de 2021). 10.4 Todas as sanções previstas nesta Ata de Registro de Preços poderão ser aplicadas cumulativamente com a multa (art. 156, 7, da Lei n 14.133, de 2021). 10.5 Antes da aplicação da multa será facultada a defesa do interessado no prazo de 15 (quinze) dias úteis, contado da data de sua intimação (art. 157, da Lei n 14.133, de 2021). 10.6 Se a multa aplicada e as indenizações cabíveis forem superiores ao valor do pagamento eventualmente devido pelo Contratante ao Contratado, além da perda desse valor, a diferença será descontada da garantia prestada ou será cobrada judicialmente (art. 156, 8, da Lei n 14.133, de 2021). 10.7 Previamente ao encaminhamento à cobrança judicial, a multa poderá ser recolhida administrativamente no prazo máximo de 30 (trinta) dias, a contar da data do recebimento da comunicação enviada pela autoridade competente. 10.8 A aplicação das sanções realizar-se-á em processo administrativo que assegure o contraditório e a ampla defesa ao Contratado, observando-se o procedimento previsto no caput e parágrafos do art. 158 da Lei n 14.133, de 2021, para as penalidades de impedimento de licitar e contratar e de declaração de inidoneidade para licitar ou contratar. 10.9 Na aplicação das sanções serão considerados (art. 156, 1, da Lei n 14.133, de 2021): 10.9.1 A natureza e a gravidade da infração cometida; 10.9.2 As peculiaridades do caso concreto; 10.9.3 As circunstâncias agravantes ou atenuantes; 10.9.4 Os danos que dela provierem para o Contratante; 10.9.5 A implantação ou o aperfeiçoamento de programa de integridade, conforme normas e orientações dos órgãos de controle. 10.10 Os atos previstos como infrações administrativas na Lei n 14.133, de 2021, ou em outras leis de licitações e contratos da Administração Pública que também sejam tipificados como atos lesivos na Lei n 12.846, de 2013, serão apurados e julgados conjuntamente, nos mesmos autos, observados o rito procedimental e autoridade competente definidos na referida Lei (art. 159). 10.11 A personalidade jurídica do Contratado poderá ser desconsiderada sempre que utilizada com abuso do direito para facilitar, encobrir ou dissimular a prática dos atos ilícitos previstos neste Contrato ou para provocar confusão patrimonial, e, nesse caso, todos os efeitos das sanções aplicadas à pessoa jurídica serão estendidos aos seus administradores e sócios com poderes de administração, à pessoa jurídica sucessora ou à empresa do mesmo ramo com relação de coligação ou controle, de fato ou de direito, com o Contratado, observados, em todos os casos, o contraditório, a ampla defesa e a obrigatoriedade de análise jurídica prévia (art. 160, da Lei n 14.133, de 2021). 10.12 O Contratante deverá, no prazo máximo 15 (quinze) dias úteis, contado da data de aplicação da sanção, informar e manter atualizados os dados relativos às sanções por ela aplicadas, para fins de publicidade no Cadastro Nacional de Empresas Inidôneas e Suspensas (CEIS) e no Cadastro Nacional de Empresas Punidas (CNEP), instituídos no âmbito do Poder Executivo Federal. (Art. 161, da Lei n 14.133, de 2021).\nAvenida da Paz, n 900 Jaraguá - MaceióAL - CEP 57022-050 CNPJ n 26.981.4550001-29 - Telefone: (82) 3312-5100 10.13 As sanções de impedimento de licitar e contratar e declaração de inidoneidade para licitar ou contratar são passíveis de reabilitação na forma do art. 163 da Lei n 14.13321. 10.14 A declaração de inidoneidade para licitar ou contratar permanecerá em vigor enquanto perdurarem os motivos determinantes da punição ou até que seja promovida a reabilitação perante a própria autoridade que aplicou a sanção, a qual será concedida sempre que a CONTRATADA ressarcir os prejuízos resultantes da sua conduta e depois de decorrido o prazo das sanções de suspensão e impedimento aplicadas. 10.15 As sanções administrativas serão aplicadas por meio da comissão de aplicação de sanções administrativas CPASA. 11 DAS DISPOSIÇÕES GERAIS 11.1 Toda alteração da presente ARP será publicada no DOEM. 11.2 A Ata de Registro de Preços somente poderá ser usada pelos Órgãos e Entidades da Administração Pública Municipal de Maceió, desde que autorizados pela Agência de Licitações, contratos e Convênios de Maceió ALICC, Órgão Gerenciador. 11.3 Em caso de licitação com critério de julgamento por GRUPO DE ITENS, as contratações futuras deverão ser realizadas, em regra, de forma proporcional para todos os itens de cada grupo, salvo justificativa técnica e desde que o valor registrado seja igual ou inferior aos preços contidos nas propostas dos demais licitantes, conforme jurisprudência do TCU. 11.4 A existência desta ARP não obriga a Administração a contratar, facultando-se a realização de licitação específica para a aquisição pretendida, assegurada preferência ao fornecedor registrado em igualdade de condições. 11.5 Os casos omissos desta ARP serão resolvidos de acordo com legislação vigente, particularmente com a Lei Federal n. 14.1332021, regulamentada pelo Decreto Municipal ns. 9.5142023. 11.6 O preço, quantitativo, fornecedor e as especificações resumidas do objeto registrado, como também suas possíveis alterações e cancelamento, serão publicados, em forma de extrato, no Diário Oficial Eletrônico do Município de Maceió - DOEM. 11.7 Todas as informações do presente registro de preço serão disponibilizadas, durante sua vigência, no site do ÓRGÃO GERENCIADOR na Internet ( inclusive com a íntegra da ARP e alterações posteriores.\nAvenida da Paz, n 900 Jaraguá - MaceióAL - CEP 57022-050 CNPJ n 26.981.4550001-29 - Telefone: (82) 3312-5100 12 DO FORO: 12.1 Para dirimir questões oriundas da presente ARP será competente o foro da Cidade de Maceió, Estado de Alagoas. Maceió, AL de de 2025. MEIRY SOARES PORCIÚNCULA DIRETORA PRESIDENTE AGÊNCIA DE LICITAÇÕES CONTRATOS E CONVÊNIOS DE MACEIÓ ÓRGÃO GERENCIADOR JULIANA OLIVIA DE AZEVEDO LIMA CÂMARA REPRESENTANTE LEGAL J O DE A L C LTDA FORNECEDOR BENEFICIÁRIO MEIRY SOARES PORCIUNCULA:240 73105434 Assinado de forma digital por MEIRY SOARES PORCIUNCULA:24073105434 Dados: 2025.08.29 12:15:45 -03'00' 29\nAvenida da Paz, n 900 Jaraguá - MaceióAL - CEP 57022-050 CNPJ n 26.981.4550001-29 - Telefone: (82) 3312-5100 Item Unidade de Medida Órgão Gerenciador Quant total Percentual Descrição ALICC SEMDES SMS 19 Extrato de tomate - Embalagem de 1080g UND 0 8722 0 8722 Ampla 89 20 Sardinha comestível em lata - Embalagem de 200g. UND 0 22606 0 22606 Ampla 89 27 Manteiga com sal, embalagem com 200g, UND 0 4488 0 4488 Cota 11 28 Biscoito tipo cream cracker 400g - Pacote de 400g. PCT 0 1782 58 1840 Cota 11 31 Sardinha comestível em lata - Embalagem de 200g. UND 0 2794 0 2794 Cota 11\nENDEREÇOS DE ENTREGA DOS ÓRGÃOS PARTICIPANTES ENDEREÇOS DE ENTREGA Órgão Gerenciador Endereço para entrega Contato ALICC Avenida da Paz, 900, Jaraguá, MaceióAL, CEP: 57022-050 (82) MaceióAL 3315-5100 Órgão Endereço para entrega Contato SEMDES Rua Barão de Atalaia. 753 (82) 3312-5923 SMS RUA GENERAL HERMES, 1199 - CAMBONA (82) 3315-5100 SEMDES SEMDES SEDE av. Comendador Leão, 1383, Poço, Maceió-AL unidades de Serviços - ENDEREÇO PARA ENTREGA CRAS - Pitanguinha Rua Cônego Valente Tobias sn Pitanguinha - Maceió AL 3 Região - Telefone: (82)3312-5955 CRAS Santos Dumont Rua Roldão de Siqueira Fortes, 710 Santos Dumont, (corredor de ônibus) - Telefone: (82)3312-5957 CRAS Cacilda Sampaio Rua das Flores sn, Vergel - Telefone: (82) 3312-5949 CRAS - Bela Vista R: Cel. Salustiano n 310. Sitio São Jorge - Telefone: (82)3312-5947 CRAS Rio Novo R Da Areia, 11529, - Rio Novo- Telefone: (82)3312-5956 CRAS Selma Bandeira Conjunto Selma Bandeira, SN, Benedito Bentes, CEP: 57085-190 - Maceió AL - Telefone: (82)3312-5958 (82) 3354-1767 (82) 988371481 CRAS - Bebedouro Rua Marquês de Abrantes, sn Bebedouro - Telefone: (82)3312-5946 CRAS Fernão Velho Praça São José, 37 - Telefone: (82)3312-5954 CRAS Clima Bom Conjunto Residencial Osman Loureiro, n 242 Lote 10, Qd. C1, Tabuleiro do Martins (Funcionamento: segunda à sexta). CRAS Bom Parto R: General Hermes, 1752 Cambona - Telefone: (82)3312-5948 CRAS Cidade Sorriso Rua C-22 (Quadra C-24, lote 15) Conjunto Residencial Benedito Bentes II. Telefone: (82)3312-5950 (82) 98752-2233 CRAS - Denisson Menezes Rua Rosivaldo Ferreira Mendes 434 Q D3 Lote 46 - Cidade Universitária CRAS - Área Lagunar Rua Ângelo Barbosa, n 527 Prado Telefone: (82) (82)3312-5945 (82) 3315-6418 (82) 98897-2404 CRAS Litoral Norte Av. Gal. Luiz de França Albuquerque, SN - Quadra 42, Lote 305 (Rodovia 101 Norte) - Bairro Riacho Doce Serviços Abrigos ENDEREÇO PARA ENTREGA ACOLHER Rua Alameda das Manhãs, n 28, Gruta CEP 57052770 Telefone: (82)3312-5916 (82)98882-8239 ALBERGUE Avenida Comendador Leão, sn. Poço. Esquina com o SENAI. Telefone: (82)3312-5917 CASA DE ADOÇÃO Rua Dr. Alfredo Oiticica n 288 Pitanguinha 57052-230 Telefone: (82)3312-5918 (82) 8882-8213 VIVA VIDA Rua Engenheiro Otávio Cabral, n 203 - Gruta de Lourdes. Telefone: (82)3312-5922 (82) 98876-6117 (82) 98861-9005 (82) 98892- 7943 CASA DE PASSAGEM FEMININA Rua Des. Barreto Cardoso, n 428, Gruta de Lourdes - CEP: 57052-850 - Telefone: (82)3312-5920 (82)98882-8238 (82)99656-1373\nCASA DE PASSAGEM FAMILIAR Ladeira Rosalvo Ribeiro, n 87- Centro Telefone: (82)3312-5919 99623-8981 (82) 99624- 9776 (82) 98886-5065 CASA LAR Rua Antônio Morais Costa, n6- Feitosa Quadra C, Lote 18 57043-630 - Telefone: (82)3312-5921 (82) 98846-7467 CIDADE DO IDOSO Av. Durval de Góes Monteiro, (antiga SMTT) - Tabuleiro dos Martins Novo Albergue Benedito Bentes - Unidade de Acolhimento para População de Rua Parte Alta .Rua Alice Uchoa Botelho, 650, Benedito Bentes, Qd. A-12, Lote: 0348, CEP. 57.084-011 CENTROS POP I, II e III ENDEREÇO PARA ENTREGA CENTRO POP I Endereço: Avenida da Paz, 994, Jaraguá Telefone: (82)3312-5931 (82) 98816-5101 0800 284 8048 CENTRO POP II Av. Tomás Espínola, N 86 Farol (em processo de mudança) Telefone: (82)3312-5932 (82) 99970-7035 CENTRO POP III Rua Estudante Sanelva Antônio Pedrosa Pereira, 506, Benedito Bentes, QD. B-42, Lote 0187, CEP. 57.085-733 SERVIÇOS DE CONVIVÊNCIA ENDEREÇO PARA ENTREGA Serviço de Convivência Rua Celestino Chagas da Silva, n 103; QD-P; Lote: 03; CAIC UFAL Tabuleiro Loteamento Jardim da Saúde; Bairro Cidade UniversitáriaAL Telefone: (82)3312-5925 (82) 98838-7905 Serviço de Convivência (Josenópolis) Rua Marquês de Abrantes, sn Bebedouro MaceióAL CEP: 57.017-601 - Telefone: (82) 3312-5966 Serviço de Convivência (Lar São Domingos) Av. Comendador Gustavo Paiva, 4291 - Mangabeiras, Maceió - AL, 57031-530 - Telefone: (82) 2121-13003312-5967 Secretaria Municipal de Saúde- SMS Rua Dias Cabral, 569 - Centro CEP 57020-250 Telefone: 82 3312-5400 Central de Abastecimento Farmacêutico ENDEREÇO PARA ENTREGA Central de Abastecimento Farmacêutico CAF Avenida Juca Sampaio, 620, Barro Duro, CEP: 57.045-365, Maceió-AL - (82) 3312-5447 unidades de Serviços - ENDEREÇO PARA ENTREGA PAM SALGADINHOCEO PAM SALGADINHO Avenida do Ferroviário (Antiga Rua Mizael Domingues), 241, Centro, Maceió (AL), CEP 57.020-600 UNIDADE DE SAÚDE DA FAMÍLIA REGINALDO Rua Doutor Carlos Miranda, 96, Poço, Maceió (AL), CEP 57025- 790 CENTRO ESPECIALIZADO ELIANE MACHADO Avenida do Ferroviário (Antiga Rua Mizael Domingues), Centro, Maceió (AL) CAPS II DR. ROSTAN SILVESTRE Rua José Maia Gomes, SN, Jatiúca, Maceió (AL), CEP 57036-240 UNIDADE BÁSICA DE SAÚDE OSVALDO BRANDÃO VILELA Rua Lafaiete Pacheco, SN, Ponta da Terra, Maceió (AL), CEP 57030-646 - (82) 3312-5498 UNIDADE DE REFERÊNCIA EM SAÚDE DR. DIÓGENES JUCÁ BERNARDES II CENTRO Praça da Maravilha, SN, Poço, Maceió (AL), CEP 57025-860 - Telefone: 3312-5499 UNIDADE BÁSICA DE SAÚDE PAM DIQUE ESTRADA Rua das Flores, SN, Conj. Joaquim Leão, Ponta Grossa, Maceió (AL), CEP 57014-600 Telefone: 3312-5502 UNIDADE REFERÊNCIA DE SAÚDE ROLAND SIMON Rua Cabo Reis, SN, Vergel do Lago, Maceió (AL), CEP: 57015- 520; Telefone: 3312-5503\nCADASTRO DE RESERVA 1 CLASSIFICADA EMPRESA: CNPJ: Telefone: e-mail: Endereço: GRUPO ITEM QUANT DESCRIÇAO MARCA UNID. PREÇO (R) 01 01 02 2 CLASSIFICADA EMPRESA: CNPJ: Telefone: e-mail: Endereço: GRUPO ITEM QUANT DESCRIÇAO MARCA UNID. PREÇO (R) 01 01 02", "target": "{\n  \"Documento\": {\n    \"Numero_ARP\": \"482/2025- CPL/ALICC\",\n    \"Numero_Processo\": \"12500.129688/2024\",\n    \"Pregao_Eletronico\": \"N° 134/2025-CPL/ALICC\"\n  },\n  \"Orgao_Gerenciador\": {\n    \"Razao_Social\": \"AGÊNCIA DE LICITAÇÕES, CONTRATOS E CONVÊNIOS DE MACEIÓ ALICC\",\n    \"CNPJ\": \"26.981.455/0001-29\",\n    \"UG\": \"\",\n    \"Endereco\": \"Avenida da Paz, n.º 900, Jaraguá, Maceió/AL-57.022-050\",\n    \"Representantes_Legais\": [\n      {\n        \"Cargo\": \"Diretora Presidente\",\n        \"Nome\": \"MEIRY SOARES PORCIÚNCULA\"\n      }\n    ]\n  },\n  \"Fornecedor\": {\n    \"Razao_Social\": \"JODEAL CLTDA\",\n    \"CNPJ\": \"44.346.537/0001-83\",\n    \"Endereco\": \"Av. Siqueira Campos N°1747 A, Bairro: Trapiche Da Barra, Maceió/AL - CEP: 57010-395\",\n    \"Telefone\": \"(82)-988743536\",\n    \"Email\": \"edvaldocamara@gmail.com\",\n    \"Representante_Legal\": \"Juliana Olivia de Azevedo Lima Câmara\",\n    \"Representante_Legal_Documentos\": \"RG: 4284497-5 SSP/AL CPF 058.119.514-00\"\n  },\n  \"Itens_Registrados\": [\n    {\n      \"Item_TR\": \"19\",\n      \"Descricao_Especificacao\": \"Extrato de tomate - a base de: tomate, açúcar (máximo de 1%), sal (máximo de 5% de cloreto de sódio); isento de fermentações. O produto deverá apresentar validade mínima de 12 meses da entrega. Embalagem de 1080g\",\n      \"Marca_Modelo\": \"Quero\",\n      \"Codigo\": \"\",\n      \"Unidade_Medida\": \"Und\",\n      \"Quantidade_Registrada\": \"8722\",\n      \"Valor_Unitario\": \"12,99\",\n      \"Valor_Total_Item\": \"113.298,78\"\n    },\n    {\n      \"Item_TR\": \"20\",\n      \"Descricao_Especificacao\": \"Sardinha comestível em lata em conserva, tipo pescada em conserva, apresentação inteira, com espinha e óleo comestível, contendo ômega 3. Embalagem contendo o registro e informações nutricionais do Ministério da Agricultura, data de validade e o SIF/DIPOA. O produto deverá apresentar validade mínima de 12 meses da entrega. Embalagem de 200g.\",\n      \"Marca_Modelo\": \"GDC Alimentos\",\n      \"Codigo\": \"\",\n      \"Unidade_Medida\": \"Und\",\n      \"Quantidade_Registrada\": \"22606\",\n      \"Valor_Unitario\": \"4,95\",\n      \"Valor_Total_Item\": \"111.899,70\"\n    },\n    {\n      \"Item_TR\": \"27\",\n      \"Descricao_Especificacao\": \"Manteiga com sal, contendo dados de identificação do produto, marca do fabricante, prazo de validade e peso líquido. O produto deverá ter registro no Ministério da Saúde e/ou Agricultura, em embalagens e temperaturas corretas (10°c ou de acordo com o fabricante) e adequadas, respeitando a características do produto. De modo que a embalagem não se apresente estufadas ou alteradas. Embalagem com 200g.\",\n      \"Marca_Modelo\": \"Betânia\",\n      \"Codigo\": \"\",\n      \"Unidade_Medida\": \"Und\",\n      \"Quantidade_Registrada\": \"4488\",\n      \"Valor_Unitario\": \"11,99\",\n      \"Valor_Total_Item\": \"53.811,12\"\n    },\n    {\n      \"Item_TR\": \"28\",\n      \"Descricao_Especificacao\": \"Biscoito tipo cream cracker 400g - biscoito com sal, elaborado com composição básica de farinha de trigo, sal, enriquecida com ferro e ácido fólico, outras substâncias permitidas, acondicionado em embalagem primária plástica atóxica, íntegra, transparente; rótulo contendo: identificação do produto, ingredientes, valor nutricional, peso, fabricante, data de fabricação. O produto deverá apresentar validade mínima de 6 meses da entrega. Pacote de 400g.\",\n      \"Marca_Modelo\": \"3 de Maio\",\n      \"Codigo\": \"\",\n      \"Unidade_Medida\": \"Pct\",\n      \"Quantidade_Registrada\": \"1840\",\n      \"Valor_Unitario\": \"4,44\",\n      \"Valor_Total_Item\": \"8.169,60\"\n    },\n    {\n      \"Item_TR\": \"31\",\n      \"Descricao_Especificacao\": \"Sardinha comestível em lata em conserva, tipo pescada em conserva, apresentação inteira, com espinha e óleo comestível, contendo ômega 3. Embalagem contendo o registro e informações nutricionais do Ministério da Agricultura, data de validade e o SIF/DIPOA. O produto deverá apresentar validade mínima de 12 meses da entrega. Embalagem de 200g.\",\n      \"Marca_Modelo\": \"GDC Alimentos\",\n      \"Codigo\": \"\",\n      \"Unidade_Medida\": \"Und\",\n      \"Quantidade_Registrada\": \"2794\",\n      \"Valor_Unitario\": \"4,95\",\n      \"Valor_Total_Item\": \"13.830,30\"\n    }\n  ],\n  \"Valor_Total\": \"R$ 301.009,50\"\n}"}
